aria2_dht_dat_parser-0.1.0.dist-info/METADATA
aria2_dht_dat_parser-0.1.0.dist-info/WHEEL
aria2_dht_dat_parser-0.1.0.dist-info/entry_points.txt
aria2_dht_dat_parser-0.1.0.dist-info/licenses/LICENSE
aria2_dht_dat_parser/__init__.py
aria2_dht_dat_parser/__main__.py
aria2_dht_dat_parser/parser.py
aria2_dht_dat_parser-0.1.0.dist-info/RECORD
