Metadata-Version: 2.1
Name: aria2-dht-dat-parser
Version: 0.1.0
Summary: parse aria2's dht.dat into human-readable json
Author-Email: yixinBC <yixinbc@foxmail.com>
License: MIT
Requires-Python: >=3.7
